ai_code_compass/__init__.py
ai_code_compass/__main__.py
ai_code_compass/cache.py
ai_code_compass/cli.py
ai_code_compass/formatter.py
ai_code_compass/graph.py
ai_code_compass/map_generator.py
ai_code_compass/models.py
ai_code_compass/parsers/__init__.py
ai_code_compass/parsers/python_parser.py
ai_code_compass-0.1.2.dist-info/licenses/LICENSE
ai_code_compass-0.1.2.dist-info/METADATA
ai_code_compass-0.1.2.dist-info/WHEEL
ai_code_compass-0.1.2.dist-info/entry_points.txt
ai_code_compass-0.1.2.dist-info/top_level.txt
ai_code_compass-0.1.2.dist-info/RECORD
