Metadata-Version: 2.4
Name: ai-code-compass
Version: 0.1.2
Summary: Fast code map generator for AI coding assistants - Save 99%+ tokens
Author-email: Xiangyu Li <xiangyu.li@example.com>
Maintainer-email: Xiangyu Li <xiangyu.li@example.com>
License: MIT
Project-URL: Homepage, https://github.com/Xiangyu-Li97/Code-Compass-v0.1.0-MVP
Project-URL: Repository, https://github.com/Xiangyu-Li97/Code-Compass-v0.1.0-MVP
Project-URL: Bug Tracker, https://github.com/Xiangyu-Li97/Code-Compass-v0.1.0-MVP/issues
Project-URL: Documentation, https://github.com/Xiangyu-Li97/Code-Compass-v0.1.0-MVP#readme
Keywords: ai,llm,code-analysis,developer-tools,code-indexing,pagerank,ai-assistant,token-optimization
Classifier: Development Status :: 4 - Beta
Classifier: Intended Audience :: Developers
Classifier: License :: OSI Approved :: MIT License
Classifier: Operating System :: OS Independent
Classifier: Programming Language :: Python :: 3
Classifier: Programming Language :: Python :: 3.9
Classifier: Programming Language :: Python :: 3.10
Classifier: Programming Language :: Python :: 3.11
Classifier: Programming Language :: Python :: 3.12
Classifier: Topic :: Software Development :: Libraries :: Python Modules
Classifier: Topic :: Software Development :: Code Generators
Classifier: Topic :: Scientific/Engineering :: Artificial Intelligence
Requires-Python: >=3.9
License-File: LICENSE
Requires-Dist: click>=8.0.0
Provides-Extra: dev
Requires-Dist: pytest>=7.0.0; extra == "dev"
Requires-Dist: black>=23.0.0; extra == "dev"
Requires-Dist: mypy>=1.0.0; extra == "dev"
Dynamic: license-file
